magic_decorator.py
magic_decorator-0.0.12.dist-info/METADATA
magic_decorator-0.0.12.dist-info/WHEEL
magic_decorator-0.0.12.dist-info/licenses/LICENSE
magic_decorator-0.0.12.dist-info/RECORD
