Metadata-Version: 2.1
Name: magic-decorator
Version: 0.0.12
Summary: A magic function decorator using OpenAI ChatCompletion
Author-email: Kim Minjong <make.dirty.code@gmail.com>
License-File: LICENSE
Classifier: License :: OSI Approved :: MIT License
Classifier: Operating System :: OS Independent
Classifier: Programming Language :: Python :: 3
Requires-Python: >=3.7.1
Requires-Dist: langchain
Requires-Dist: openai>0.27
Requires-Dist: sick-json
